setup.py
passweb/__init__.py
passweb/main.py
passweb.egg-info/PKG-INFO
passweb.egg-info/SOURCES.txt
passweb.egg-info/dependency_links.txt
passweb.egg-info/entry_points.txt
passweb.egg-info/not-zip-safe
passweb.egg-info/requires.txt
passweb.egg-info/top_level.txt